intropy/__init__.py
intropy/cli.py
intropy/py.typed
intropy-0.9.0.dist-info/LICENSE
intropy-0.9.0.dist-info/METADATA
intropy-0.9.0.dist-info/WHEEL
intropy-0.9.0.dist-info/entry_points.txt
intropy-0.9.0.dist-info/top_level.txt
intropy-0.9.0.dist-info/RECORD
